mcp_server/main.py
my_mcp_server-0.1.4.dist-info/METADATA
my_mcp_server-0.1.4.dist-info/WHEEL
my_mcp_server-0.1.4.dist-info/entry_points.txt
my_mcp_server-0.1.4.dist-info/top_level.txt
my_mcp_server-0.1.4.dist-info/RECORD
